wordgrid_tool.py
wordgrid_tool-0.1.3.dist-info/licenses/LICENSE
wordgrid_tool-0.1.3.dist-info/METADATA
wordgrid_tool-0.1.3.dist-info/WHEEL
wordgrid_tool-0.1.3.dist-info/entry_points.txt
wordgrid_tool-0.1.3.dist-info/top_level.txt
wordgrid_tool-0.1.3.dist-info/RECORD
