Metadata-Version: 2.4
Name: wordgrid-tool
Version: 0.1.3
Summary: A CLI tool to fetch stats and answers for the Wordgrid game.
Author-email: Rupinder Matharu <RupinderM@users.noreply.github.com>
License-Expression: MIT
Requires-Python: >=3.7
License-File: LICENSE
Requires-Dist: requests
Dynamic: license-file
